QEPPI/QEPPI.py
QEPPI/__init__.py
QEPPI/constant.py
QEPPI/util.py
QEPPI/version.py
QEPPI-0.1.11.dist-info/LICENSE
QEPPI-0.1.11.dist-info/METADATA
QEPPI-0.1.11.dist-info/WHEEL
QEPPI-0.1.11.dist-info/top_level.txt
QEPPI-0.1.11.dist-info/RECORD
