Metadata-Version: 2.1
Name: QEPPI
Version: 0.1.11
Summary: Calculation module of QEPPI
Home-page: https://github.com/ohuelab/QEPPI/
Author: blacktanktop
Author-email: blacktanktopme@gmail.com
License: MIT
Platform: UNKNOWN
Classifier: Programming Language :: Python :: 3.7
Classifier: Programming Language :: Python :: 3.8
Classifier: License :: OSI Approved :: MIT License
Classifier: Operating System :: OS Independent
Classifier: Topic :: Scientific/Engineering :: Chemistry
Classifier: Topic :: Scientific/Engineering :: Bio-Informatics
License-File: LICENSE
Requires-Dist: rdkit-pypi (>=2021.3.1.5)
Requires-Dist: numpy (>=1.19.5)
Requires-Dist: pandas (>=1.1.5)
